deepinterpolation/__init__.py
deepinterpolation/generator_collection.py
deepinterpolation/generic.py
deepinterpolation/inferrence_collection.py
deepinterpolation/loss_collection.py
deepinterpolation/network_collection.py
deepinterpolation/trainor_collection.py
deepinterpolation/cli/__init__.py
deepinterpolation/cli/fine_tuning.py
deepinterpolation/cli/inference.py
deepinterpolation/cli/schemas.py
deepinterpolation/cli/training.py
deepinterpolation-0.1.4.dist-info/LICENSE
deepinterpolation-0.1.4.dist-info/METADATA
deepinterpolation-0.1.4.dist-info/WHEEL
deepinterpolation-0.1.4.dist-info/top_level.txt
deepinterpolation-0.1.4.dist-info/RECORD
