Metadata-Version: 2.1
Name: deepinterpolation
Version: 0.1.4
Summary: Implemenent DeepInterpolation to denoise data by removing independent noise
Home-page: https://github.com/AllenInstitute/deepinterpolation
Author: Jerome Lecoq
Author-email: jeromel@alleninstitute.org
License: Allen Institute Software License – This software license is the 2-clause BSD 
Requires-Dist: tensorflow (==2.4.4)
Requires-Dist: nibabel
Requires-Dist: h5py (==2.10.0)
Requires-Dist: matplotlib
Requires-Dist: numpy
Requires-Dist: python-dateutil
Requires-Dist: scipy
Requires-Dist: tifffile
Requires-Dist: s3fs
Requires-Dist: argschema (==2.0.2)
Requires-Dist: mlflow (==1.14.1)
